sf_session/__init__.py
sf_session/sf_session.py
sf_session-0.1.2.dist-info/LICENSE
sf_session-0.1.2.dist-info/WHEEL
sf_session-0.1.2.dist-info/METADATA
sf_session-0.1.2.dist-info/RECORD
