Metadata-Version: 2.1
Name: sf-session
Version: 0.1.2
Summary: Maintain a Salesforce Connection Session.
License: BSD 3-Clause
Author: Jarvis Nederlof
Requires-Python: >=3.8
Classifier: License :: Other/Proprietary License
Classifier: Programming Language :: Python :: 3
Classifier: Programming Language :: Python :: 3.10
Classifier: Programming Language :: Python :: 3.8
Classifier: Programming Language :: Python :: 3.9
Requires-Dist: simple-salesforce (>=1.11.6)
